forensics/app/__init__.py
forensics/app/callbacks.py
forensics/app/constants.py
forensics/app/data_loader.py
forensics/app/datasets.py
forensics/app/info_texts.py
forensics/app/interface.py
forensics/app/loader.py
forensics/app/main.py
forensics/app/metrics.py
forensics/app/metrics_test.py
forensics/app/styling.py
forensics/app/url_parser.py
forensics/app/utils.py
forensics/app/plotting/__init__.py
forensics/app/plotting/main.py
forensics/app/plotting/metrics_table.py
forensics/app/plotting/multiple.py
forensics/app/plotting/single.py
forensics/app/plotting/utils.py
forensics/app/plotting_v2/__init__.py
forensics/app/plotting_v2/constants.py
forensics/app/plotting_v2/main.py
forensics/app/plotting_v2/table.py
forensics/assets/feedback_forensics_logo.png
forensics/assets/feedback_forensics_logo.png
forensics-0.1.1.dist-info/METADATA
forensics-0.1.1.dist-info/WHEEL
forensics-0.1.1.dist-info/entry_points.txt
forensics-0.1.1.dist-info/licenses/LICENSE
forensics-0.1.1.dist-info/RECORD
